LICENSE
MANIFEST.in
README.md
setup.py
tests/test_captions.py
tests/test_channel.py
tests/test_cipher.py
tests/test_cli.py
tests/test_exceptions.py
tests/test_extract.py
tests/test_helpers.py
tests/test_itags.py
tests/test_main.py
tests/test_metadata.py
tests/test_parser.py
tests/test_playlist.py
tests/test_query.py
tests/test_request.py
tests/test_streams.py
utub3/__init__.py
utub3/__main__.py
utub3/captions.py
utub3/channel.py
utub3/cipher.py
utub3/cli.py
utub3/exceptions.py
utub3/extract.py
utub3/helpers.py
utub3/innertube.py
utub3/itags.py
utub3/metadata.py
utub3/monostate.py
utub3/parser.py
utub3/playlist.py
utub3/query.py
utub3/request.py
utub3/search.py
utub3/streams.py
utub3/version.py
utub3.egg-info/PKG-INFO
utub3.egg-info/SOURCES.txt
utub3.egg-info/dependency_links.txt
utub3.egg-info/entry_points.txt
utub3.egg-info/top_level.txt
utub3.egg-info/zip-safe