Metadata-Version: 2.1
Name: utub3
Version: 1.0.0
Summary: Python 3 library for downloading YouTube Videos.
Home-page: https://github.com/pchchv/utub3
Author: Evgenii Pochechuev
Author-email: ipchchv@gmail.com
License: Apache-2.0 license
Project-URL: Bug Reports, https://github.com/pchchv/utub3/issues
Project-URL: Read the Docs, https://github.com/pchchv/utub3/docs
Keywords: youtube,download,video,stream
Classifier: Development Status :: 3 - Alpha
Classifier: Environment :: Console
Classifier: Intended Audience :: Developers
Classifier: License :: OSI Approved :: Apache Software License
Classifier: Natural Language :: English
Classifier: Operating System :: OS Independent
Classifier: Programming Language :: Python :: 3.6
Classifier: Programming Language :: Python :: 3.7
Classifier: Programming Language :: Python :: 3.8
Classifier: Programming Language :: Python :: 3.9
Classifier: Programming Language :: Python
Classifier: Topic :: Internet
Classifier: Topic :: Multimedia :: Video
Classifier: Topic :: Software Development :: Libraries :: Python Modules
Classifier: Topic :: Terminals
Classifier: Topic :: Utilities
Requires-Python: >=3.6
License-File: LICENSE
